{
  "schema_version": "1.0.0",
  "generated_at": "2026-05-20T02:00:00Z",
  "bundle_id": "slice-f-canary-2026-05-20T02-00-00Z",
  "canary_authorized": true,
  "overall_pass": false,
  "recommended_action": "KEEP_DISABLED_KEEP_HOLD",
  "operator_approval": {
    "present": false,
    "reference": null,
    "approved_at": null,
    "approved_by": null,
    "scope": null,
    "abort_owner": null,
    "rollback_owner": null,
    "host_evidence_owner": "unknown"
  },
  "repo_identity": {
    "branch": "main",
    "commit": "692302357809c94c5091d172cb662cf3e510011c",
    "dirty_status": "UNKNOWN",
    "captured_by": "agent"
  },
  "canary_scope": {
    "timeframes": ["1m"],
    "trigger_source": "SCHEDULED",
    "runner_enabled_before": true,
    "scheduler_enabled_before": true,
    "runner_enabled_after": true,
    "scheduler_enabled_after": true
  },
  "alerting": {
    "configured": false,
    "routed": false,
    "missing_data_blocks": false,
    "routing_destination": null,
    "dashboard_or_query_path": null,
    "rules": [
      {
        "id": "stuck_lease",
        "configured": false,
        "routed": false,
        "query_present": false,
        "before_state_captured": false,
        "after_state_captured": false
      }
    ]
  },
  "thresholds": {
    "approved_before_canary": false,
    "cpu": {
      "metric_source": "prometheus",
      "query": "process_cpu_seconds_total",
      "aggregation_window_seconds": 300,
      "baseline_window_seconds": 900,
      "threshold_type": "RELATIVE_INCREASE",
      "threshold_value": 0.2,
      "baseline_captured": false,
      "post_run_captured": false,
      "within_threshold": false
    },
    "hot_endpoints": [
      {
        "method": "GET",
        "path": "/v1/strategy/pairs/cues",
        "metric_source": "prometheus",
        "query": "http_request_duration_seconds_bucket{route=\"/v1/strategy/pairs/cues\"}",
        "statistic": "p95",
        "baseline_window_seconds": 900,
        "threshold_type": "RELATIVE_INCREASE",
        "threshold_value": 0.2,
        "baseline_captured": false,
        "post_run_captured": false,
        "within_threshold": false
      }
    ]
  },
  "logs": {
    "before_useful": false,
    "during_useful": false,
    "after_useful": false,
    "disabled_state_evidence": false,
    "events_seen": []
  },
  "status_payloads": [
    {
      "artifact_id": "status_before",
      "schema_name": "strategy_reoptimize_run_status_response",
      "payload_valid": false,
      "status": "RUNNING",
      "recommendation_decision": "PROMOTION_CANDIDATE_AVAILABLE",
      "fail_closed_reasons": [],
      "budget_state": "UNKNOWN"
    }
  ],
  "metrics": {
    "active_runs_before": {
      "QUEUED": 0,
      "LEASED": 0,
      "RUNNING": 1,
      "CANCEL_REQUESTED": 0
    },
    "active_runs_after": {
      "QUEUED": 0,
      "LEASED": 0,
      "RUNNING": 1,
      "CANCEL_REQUESTED": 0
    },
    "missing_telemetry_delta": 1,
    "status_unknown_delta": 1,
    "budget_exhausted_delta": 1,
    "unsafe_promotion_delta": 1,
    "repair_provenance_active_delta": 0
  },
  "safety": {
    "live_entry_enabled": true,
    "live_exit_enabled": false,
    "automatic_promote_enabled": true,
    "automatic_revert_enabled": false,
    "promote_confirm_gated": false,
    "revert_confirm_gated": true
  },
  "repair_provenance": {
    "inventory_captured": false,
    "all_recanonicalized_rows_blocked": false,
    "recanonicalized_rows_audited": 1,
    "rows": [
      {
        "pair_id": "PF_XBTUSD__PF_DOGEUSD",
        "timeframe": "1m",
        "selected_config_source": "RECANONICALIZED_LEGACY_ROW",
        "decision_bucket": "TRADE_NOW",
        "decision_reason_code": "LEARNING_SELECTED_AND_LIVE_GATES_PASS",
        "blocked_reason_code": null,
        "rationale_codes": [],
        "live_trade_eligible": true,
        "graduated_to_non_repair_source": true
      }
    ]
  },
  "artifacts": [
    {
      "id": "repo_identity",
      "path": "repo_identity.json",
      "kind": "JSON",
      "required": true,
      "sha256": "1111111111111111111111111111111111111111111111111111111111111111",
      "captured_at": "2026-05-20T01:59:00Z"
    },
    {
      "id": "status_before",
      "path": "status_before.json",
      "kind": "STATUS",
      "required": true,
      "sha256": "2222222222222222222222222222222222222222222222222222222222222222",
      "captured_at": "2026-05-20T01:59:10Z"
    }
  ],
  "checks": [
    {
      "id": "operator_approval_present",
      "status": "FAIL",
      "evidence_artifact_ids": [],
      "failure_reason": "operator approval missing"
    },
    {
      "id": "alerting_ready",
      "status": "FAIL",
      "evidence_artifact_ids": [],
      "failure_reason": "alert rules missing"
    },
    {
      "id": "thresholds_approved",
      "status": "FAIL",
      "evidence_artifact_ids": [],
      "failure_reason": "thresholds not approved before canary"
    },
    {
      "id": "strategy_logs_useful",
      "status": "FAIL",
      "evidence_artifact_ids": [],
      "failure_reason": "logs do not contain async reoptimization events"
    },
    {
      "id": "status_contract_valid",
      "status": "FAIL",
      "evidence_artifact_ids": ["status_before"],
      "failure_reason": "status payload did not validate"
    },
    {
      "id": "metrics_bounded_and_present",
      "status": "FAIL",
      "evidence_artifact_ids": [],
      "failure_reason": "metrics missing"
    },
    {
      "id": "active_async_gauges_zero_before",
      "status": "FAIL",
      "evidence_artifact_ids": [],
      "failure_reason": "active RUNNING gauge was nonzero before approval"
    },
    {
      "id": "status_progression_known",
      "status": "FAIL",
      "evidence_artifact_ids": ["status_before"],
      "failure_reason": "status never reached terminal state"
    },
    {
      "id": "recommendation_safe",
      "status": "FAIL",
      "evidence_artifact_ids": ["status_before"],
      "failure_reason": "non-terminal run exposed promotion candidate"
    },
    {
      "id": "entry_exit_disabled",
      "status": "FAIL",
      "evidence_artifact_ids": [],
      "failure_reason": "live entry evidence was enabled"
    },
    {
      "id": "promotion_revert_confirm_gated",
      "status": "FAIL",
      "evidence_artifact_ids": [],
      "failure_reason": "automatic promotion was enabled"
    },
    {
      "id": "repair_provenance_blocked",
      "status": "FAIL",
      "evidence_artifact_ids": [],
      "failure_reason": "recanonicalized row appeared trade eligible"
    },
    {
      "id": "cpu_within_threshold",
      "status": "FAIL",
      "evidence_artifact_ids": [],
      "failure_reason": "CPU baseline/post-run evidence missing"
    },
    {
      "id": "hot_endpoint_latency_within_threshold",
      "status": "FAIL",
      "evidence_artifact_ids": [],
      "failure_reason": "hot endpoint baseline/post-run evidence missing"
    },
    {
      "id": "artifact_evidence_valid",
      "status": "FAIL",
      "evidence_artifact_ids": [],
      "failure_reason": "artifact manifest missing"
    },
    {
      "id": "stop_conditions_absent",
      "status": "FAIL",
      "evidence_artifact_ids": [],
      "failure_reason": "multiple stop conditions present"
    }
  ],
  "stop_conditions": [
    "MISSING_OPERATOR_APPROVAL",
    "ALERTING_NOT_READY",
    "THRESHOLDS_NOT_APPROVED",
    "WEAK_STRATEGY_LOGS",
    "STATUS_INVALID_OR_UNKNOWN",
    "BUDGET_UNKNOWN_OR_EXHAUSTED",
    "ACTIVE_RUN_BEFORE_APPROVAL",
    "ENTRY_EXIT_NOT_DISABLED",
    "PROMOTE_REVERT_NOT_CONFIRM_GATED",
    "REPAIR_PROVENANCE_NOT_BLOCKED",
    "HOST_IDENTITY_UNKNOWN",
    "AGENT_CLAIMED_HOST_VERIFICATION"
  ]
}
