{
  "timeframe": "1m",
  "generated_at": "2026-02-19T02:11:00Z",
  "gates": [
    {
      "pair_id": "PI_XBTUSD__PI_ETHUSD",
      "left_instrument": "PI_XBTUSD",
      "right_instrument": "PI_ETHUSD",
      "timeframe": "1m",
      "expected_edge_bps": 7.42,
      "fee_bps": 1.2,
      "funding_model": "DYNAMIC",
      "funding_events": 0,
      "funding_bps_per_event": 0.6,
      "funding_bps": 0.3,
      "slippage_bps": 1.84,
      "net_edge_bps": 4.08,
      "pass": true,
      "setup_pass": true,
      "trade_ready": true,
      "trade_blocked_by": "NONE",
      "rationale_codes": ["PERFORMANCE_GATE_SOURCE_PAPER_TRADES", "SLIPPAGE_SOURCE_SAMPLED"]
    },
    {
      "pair_id": "PI_SOLUSD__PI_ETHUSD",
      "left_instrument": "PI_SOLUSD",
      "right_instrument": "PI_ETHUSD",
      "timeframe": "1m",
      "expected_edge_bps": 1.41,
      "fee_bps": 1.2,
      "funding_model": "DYNAMIC",
      "funding_events": 0,
      "funding_bps_per_event": 0.6,
      "funding_bps": 0.3,
      "slippage_bps": 1.55,
      "net_edge_bps": -1.64,
      "pass": false,
      "setup_pass": true,
      "trade_ready": false,
      "trade_blocked_by": "COST",
      "rationale_codes": [
        "PERFORMANCE_GATE_SOURCE_PAPER_TRADES",
        "SLIPPAGE_SOURCE_SAMPLED",
        "PERFORMANCE_GATE_BLOCKED"
      ]
    }
  ],
  "skipped": []
}
